Workbook

Sheet Lisez-moi
A1: Value tree quantifiée — assureur type (cas d'école fictif)
A2: Fichier de calcul livré avec le deck « L'IA en assurance et en actuariat » — Accenture Insurance & Actuarial — 7 octobre 2026
A4: Conventions
A5: Texte bleu sur fond jaune = hypothèse modifiable (onglet Hypothèses et colonnes H à L de l'onglet Blocs). Texte noir = formule. Texte vert = lien vers un autre onglet.
A6: Formule du book : impact annuel = base concernée × part adressable × effet unitaire × taux d'adoption × montée en charge − coût de possession.
A7: Les montants sont en millions d'euros (M€) ; les taux sont stockés en fractions (0,12 = 12 %).
A9: Onglets
A10: Hypothèses : paramètres de l'assureur type (primes, S/P, effectifs, coûts, capital, montée en charge, coût de possession).
A11: Blocs : les 17 blocs de valeur, leur base (formules vers Hypothèses), leurs effets unitaires bas/haut, leur preuve (sourcé / expert) et leurs sources.
A12: Résultats : valeur annuelle en régime de croisière par levier et par maillon, ratio combiné avant/après, en % des primes.
A13: Trajectoire : montée en charge 2027-2030, coût de possession, valeur nette et cumul, point mort.
A14: Sensibilités : variation de la valeur nette de croisière autour du cas médian, une hypothèse à la fois.
... A20: Sources des effets unitaires : fiches de benchmark du book (chapitre 11) ; identifiants de fiches rappelés dans l'onglet Blocs.

Sheet Hypothèses
A1: Hypothèses de l'assureur type (modifiables : cellules bleues sur fond jaune)
A2: Années : colonnes B à E = 2027 à 2030 pour la montée en charge et le coût fixe
A4: Primes émises par ligne (M€)
A5: Primes Automobile | B5: 1200 | C5: Hypothèse de structure
A6: Primes Habitation | B6: 800 | C6: Hypothèse de structure
A7: Primes Santé | B7: 600 | C7: Hypothèse de structure
A8: Primes Prévoyance | B8: 400 | C8: Hypothèse de structure
A9: Primes Vie, épargne, retraite | B9: 1500 | C9: Hypothèse de structure
A10: Primes Entreprises et RC | B10: 500 | C10: Hypothèse de structure
A12: Ratio sinistres / primes par ligne (hors vie)
A13: S/P Automobile | B13: 0.72 | C13: Hypothèse de structure
A14: S/P Habitation | B14: 0.66 | C14: Hypothèse de structure
A15: S/P Santé | B15: 0.83 | C15: Hypothèse de structure
A16: S/P Prévoyance | B16: 0.62 | C16: Hypothèse de structure
A17: S/P Entreprises et RC | B17: 0.63 | C17: Hypothèse de structure
A19: Effectifs (ETP) et coûts
A20: ETP sinistres (dont prestations santé) | B20: 1500 | C20: Total 6 000 ETP
A21: ETP souscription et gestion des contrats | B21: 1100 | C21: Total 6 000 ETP
A22: ETP distribution et support commercial | B22: 800 | C22: Total 6 000 ETP
A23: ETP relation client | B23: 700 | C23: Total 6 000 ETP
A24: ETP actuariat, finance, risques, conformité | B24: 450 | C24: Total 6 000 ETP
A25: ETP IT et data | B25: 850 | C25: Total 6 000 ETP
A26: ETP fonctions support | B26: 600 | C26: Total 6 000 ETP
A27: Coût chargé moyen par ETP (M€) | B27: 0.085 | C27: 0,085 M€ = 85 k€
A28: Frais internes totaux (M€) | B28: 620 | C28: dont personnel 510 M€
A29: Commissions / primes non-vie | B29: 0.11
A31: Autres références
A32: Fraude détectée aujourd'hui (M€/an) | B32: 20 | C32: Base du bloc L1
A33: SCR (M€) | B33: 1800
A34: Coût du capital | B34: 0.06 | C34: Taux de la marge de risque Solvabilité II (6 %)
A35: Rétention annuelle auto + habitation | B35: 0.87 | C35: Référence cockpit
A36: Part des affaires nouvelles dans le portefeuille particuliers | B36: 0.15 | C36: Base du bloc G2
A37: Part de contacts clients simples (adressable E3) | B37: 0.6
A39: Marges de contribution appliquées à la croissance
A40: Marge sur primes particuliers | B40: 0.08 | C40: Hypothèse
A41: Marge sur primes entreprises | B41: 0.1 | C41: Hypothèse
A42: Valeur des affaires nouvelles vie (% de collecte) | B42: 0.03 | C42: Hypothèse
A44: Répartition des effectifs sinistres et souscription par ligne (pour la lecture par ligne)
A45: Part des ETP sinistres · Automobile | B45: 0.4 | C45: Hypothèse (lecture par ligne, non utilisée dans les totaux)
A46: Part des ETP sinistres · Habitation | B46: 0.25 | C46: Hypothèse (lecture par ligne, non utilisée dans les totaux)
A47: Part des ETP sinistres · Santé | B47: 0.2 | C47: Hypothèse (lecture par ligne, non utilisée dans les totaux)
A48: Part des ETP sinistres · Prévoyance | B48: 0.08 | C48: Hypothèse (lecture par ligne, non utilisée dans les totaux)
A49: Part des ETP sinistres · Entreprises et RC | B49: 0.07 | C49: Hypothèse (lecture par ligne, non utilisée dans les totaux)
A51: Montée en charge : part de l'effet de croisière atteinte (2027, 2028, 2029, 2030)
A52: Frais (effet rapide) | B52: 0.15 | C52: 0.45 | D52: 0.75 | E52: 0.95 | F52: fast
A53: Sinistres / primes (décalage 12-24 mois) | B53: 0.05 | C53: 0.25 | D53: 0.55 | E53: 0.85 | F53: lag
A54: Croissance | B54: 0.1 | C54: 0.35 | D54: 0.65 | E54: 0.9 | F54: mid
A55: Capital | B55: 0 | C55: 0.2 | D55: 0.5 | E55: 0.8 | F55: slow
A57: Coût de possession fixe par an (M€) : 2027, 2028, 2029, 2030
A58: Plateforme et socles | B58: 10 | C58: 10 | D58: 9 | E58: 9
A59: Intégration aux systèmes cœur | B59: 6 | C59: 6 | D59: 6 | E59: 3
A60: Données et qualité | B60: 4 | C60: 4 | D60: 3 | E60: 3
A61: Conduite du changement et formation | B61: 3 | C61: 3 | D61: 2 | E61: 2
A62: Conformité et contrôle | B62: 2 | C62: 2 | D62: 2 | E62: 2
A63: Coût variable (modèles, licences, contrôle résiduel) en % de la valeur brute | B63: 0.1

Sheet Blocs
A1: Bloc | B1: Levier | C1: Maillon | D1: Mécanisme | E1: Preuve | F1: Fiches sources (book) | G1: Base (M€) — formule | H1: Part adressable | I1: Effet unitaire bas | J1: Effet unitaire haut | K1: Facteur résultat | L1: Montée en charge | M1: Indicateur bas | N1: Indicateur haut | O1: Unité | P1: Résultat bas (M€/an) | Q1: Résultat haut (M€/an)
A2: E1 | B2: Frais | C2: Sinistres | D2: Sinistres : instruction et règlement | E2: Sourcé | F2: accenture-genai-hours, allianz-nemo, allstate-genai, pingan-life | G2: =Hypothèses!$B$20*Hypothèses!$B$27 -> 127.5 | H2: 1 | I2: 0.12 | J2: 0.25 | K2: 1 | L2: fast | M2: =G2*H2*I2 -> 15.3 | N2: =G2*H2*J2 -> 31.875 | O2: M€ | P2: =M2*K2 -> 15.3 | Q2: =N2*K2 -> 31.875
A3: E2 | B3: Frais | C3: Souscription | D3: Souscription et contrats : ingestion | E3: Sourcé | F3: zurich-sixfold, hiscox-google, swissre-uwease, manulife-maude | G3: =Hypothèses!$B$21*Hypothèses!$B$27 -> 93.5 | H3: 1 | I3: 0.1 | J3: 0.22 | K3: 1 | L3: fast | M3: =G3*H3*I3 -> 9.35 | N3: =G3*H3*J3 -> 20.57 | O3: M€ | P3: =M3*K3 -> 9.35 | Q3: =N3*K3 -> 20.57
A4: E3 | B4: Frais | C4: Contrats | D4: Relation client : contacts automatisés | E4: Sourcé | F4: pingan-ai, allstate-genai, eiopa-genai | G4: =Hypothèses!$B$23*Hypothèses!$B$27 -> 59.5 | H4: =Hypothèses!$B$37 -> 0.6 | I4: 0.24 | J4: 0.4 | K4: 1 | L4: fast | M4: =G4*H4*I4 -> 8.568 | N4: =G4*H4*J4 -> 14.28 | O4: M€ | P4: =M4*K4 -> 8.568 | Q4: =N4*K4 -> 14.28
A5: E4 | B5: Frais | C5: Distribution | D5: Distribution : copilotes conseillers | E5: Sourcé | F5: marsh-lenai, accenture-genai-hours | G5: =Hypothèses!$B$22*Hypothèses!$B$27 -> 68 | H5: 1 | I5: 0.05 | J5: 0.12 | K5: 1 | L5: fast | M5: =G5*H5*I5 -> 3.4 | N5: =G5*H5*J5 -> 8.16 | O5: M€ | P5: =M5*K5 -> 3.4 | Q5: =N5*K5 -> 8.16
A6: E5 | B6: Frais | C6: Actuariat | D6: Actuariat, finance, risques augmentés | E6: Sourcé | F6: accenture-genai-hours, scor-ai, soa-llm | G6: =Hypothèses!$B$24*Hypothèses!$B$27 -> 38.25 | H6: 1 | I6: 0.08 | J6: 0.18 | K6: 1 | L6: fast | M6: =G6*H6*I6 -> 3.06 | N6: =G6*H6*J6 -> 6.885 | O6: M€ | P6: =M6*K6 -> 3.06 | Q6: =N6*K6 -> 6.885
A7: E6 | B7: Frais | C7: Support | D7: IT, data, support : assistants internes | E7: Sourcé | F7: axa-securegpt, marsh-lenai, accenture-genai-hours | G7: =(Hypothèses!$B$25+Hypothèses!$B$26)*Hypothèses!$B$27 -> 123.25 | H7: 1 | I7: 0.06 | J7: 0.14 | K7: 1 | L7: fast | M7: =G7*H7*I7 -> 7.395 | N7: =G7*H7*J7 -> 17.255 | O7: M€ | P7: =M7*K7 -> 7.395 | Q7: =N7*K7 -> 17.255
A8: L1 | B8: S/P | C8: Fraude | D8: Fraude : détection augmentée | E8: Sourcé | F8: generali-shift, allianz-incognito, aviva-fraud, pingan-ai | G8: =Hypothèses!$B$32 -> 20 | H8: 1 | I8: 0.4 | J8: 1 | K8: 1 | L8: lag | M8: =G8*H8*I8 -> 8 | N8: =G8*H8*J8 -> 20 | O8: M€ | P8: =M8*K8 -> 8 | Q8: =N8*K8 -> 20
A9: L2 | B9: S/P | C9: Sinistres | D9: Sinistres dommages : fuite de valeur | E9: Expert | F9: aviva-tractable, covea-tractable, allianz-nemo | G9: =Hypothèses!$B$5*Hypothèses!$B$13+Hypothèses!$B$6*Hypothèses!$B$14+Hypothèses!$B$10*Hypothèses!$B$17 -> 1707 | H9: 1 | I9: 0.004 | J9: 0.012 | K9: 1 | L9: lag | M9: =G9*H9*I9 -> 6.828 | N9: =G9*H9*J9 -> 20.484 | O9: M€ | P9: =M9*K9 -> 6.828 | Q9: =N9*K9 -> 20.484
A10: L3 | B10: S/P | C10: Sinistres | D10: Santé : contrôle des prestations | E10: Expert | F10: pingan-ai, tawuniya, bupa-arabia | G10: =Hypothèses!$B$7*Hypothèses!$B$15 -> 498 | H10: 1 | I10: 0.005 | J10: 0.015 | K10: 1 | L10: lag | M10: =G10*H10*I10 -> 2.49 | N10: =G10*H10*J10 -> 7.47 | O10: M€ | P10: =M10*K10 -> 2.49 | Q10: =N10*K10 -> 7.47
A11: L4 | B11: S/P | C11: Tarification | D11: Tarification et sélection dommages | E11: Expert | F11: ki-brit, qbe-accenture, fca-gipp, test-achats | G11: =Hypothèses!$B$5+Hypothèses!$B$6+Hypothèses!$B$10 -> 2500 | H11: 1 | I11: 0.003 | J11: 0.01 | K11: 1 | L11: lag | M11: =G11*H11*I11 -> 7.5 | N11: =G11*H11*J11 -> 25 | O11: M€ | P11: =M11*K11 -> 7.5 | Q11: =N11*K11 -> 25
A12: L5 | B12: S/P | C12: Prévention | D12: Prévention : climat, télématique | E12: Expert | F12: — | G12: =Hypothèses!$B$5*Hypothèses!$B$13+Hypothèses!$B$6*Hypothèses!$B$14 -> 1392 | H12: 1 | I12: 0.002 | J12: 0.006 | K12: 1 | L12: lag | M12: =G12*H12*I12 -> 2.784 | N12: =G12*H12*J12 -> 8.352 | O12: M€ | P12: =M12*K12 -> 2.784 | Q12: =N12*K12 -> 8.352
A13: L6 | B13: S/P | C13: Sinistres | D13: Recours, subrogation et contentieux | E13: Expert | F13: — | G13: =Hypothèses!$B$5*Hypothèses!$B$13+Hypothèses!$B$6*Hypothèses!$B$14+Hypothèses!$B$7*Hypothèses!$B$15+Hypothèses!$B$10*Hypothèses!$B$17 -> 2205 | H13: 1 | I13: 0.001 | J13: 0.003 | K13: 1 | L13: lag | M13: =G13*H13*I13 -> 2.205 | N13: =G13*H13*J13 -> 6.615 | O13: M€ | P13: =M13*K13 -> 2.205 | Q13: =N13*K13 -> 6.615
A14: G1 | B14: Croissance | C14: Contrats | D14: Rétention particuliers | E14: Expert | F14: fca-gipp | G14: =Hypothèses!$B$5+Hypothèses!$B$6 -> 2000 | H14: 1 | I14: 0.005 | J14: 0.015 | K14: =Hypothèses!$B$40 -> 0.08 | L14: mid | M14: =G14*H14*I14 -> 10 | N14: =G14*H14*J14 -> 30 | O14: M€ primes | P14: =M14*K14 -> 0.8 | Q14: =N14*K14 -> 2.4
A15: G2 | B15: Croissance | C15: Distribution | D15: Conversion, multi-équipement particuliers | E15: Expert | F15: pingan-ai | G15: =Hypothèses!$B$36*(Hypothèses!$B$5+Hypothèses!$B$6) -> 300 | H15: 1 | I15: 0.03 | J15: 0.08 | K15: =Hypothèses!$B$40 -> 0.08 | L15: mid | M15: =G15*H15*I15 -> 9 | N15: =G15*H15*J15 -> 24 | O15: M€ primes | P15: =M15*K15 -> 0.72 | Q15: =N15*K15 -> 1.92
A16: G3 | B16: Croissance | C16: Souscription | D16: Entreprises : cotation rapide, hit ratio | E16: Expert | F16: hiscox-google, ki-brit, zurich-sixfold | G16: =Hypothèses!$B$10 -> 500 | H16: 1 | I16: 0.02 | J16: 0.05 | K16: =Hypothèses!$B$41 -> 0.1 | L16: mid | M16: =G16*H16*I16 -> 10 | N16: =G16*H16*J16 -> 25 | O16: M€ primes | P16: =M16*K16 -> 1 | Q16: =N16*K16 -> 2.5
A17: G4 | B17: Croissance | C17: Distribution | D17: Vie, épargne : conseil augmenté, collecte | E17: Expert | F17: pingan-ai, generali-fr | G17: =Hypothèses!$B$9 -> 1500 | H17: 1 | I17: 0.01 | J17: 0.03 | K17: =Hypothèses!$B$42 -> 0.03 | L17: mid | M17: =G17*H17*I17 -> 15 | N17: =G17*H17*J17 -> 45 | O17: M€ primes | P17: =M17*K17 -> 0.45 | Q17: =N17*K17 -> 1.35
A18: C1 | B18: Capital | C18: Capital | D18: Capital : données, ALM, réassurance | E18: Expert | F18: baj-quantum, arxiv-quantum, sii-review | G18: =Hypothèses!$B$33 -> 1800 | H18: 1 | I18: 0.01 | J18: 0.03 | K18: =Hypothèses!$B$34 -> 0.06 | L18: slow | M18: =G18*H18*I18 -> 18 | N18: =G18*H18*J18 -> 54 | O18: M€ SCR | P18: =M18*K18 -> 1.08 | Q18: =N18*K18 -> 3.24
D20: Note : le bloc E3 n'adresse que les contacts simples (part dans Hypothèses) ; les blocs de croissance sont convertis en résultat par la marge ; le bloc C1 par le coût du capital.
D21: Montée en charge : fast = frais, lag = sinistres (12-24 mois), mid = croissance, slow = capital (courbes dans Hypothèses).

Sheet Résultats
A1: Valeur annuelle brute en régime de croisière (M€)
A3: Levier | B3: Bas | C3: Haut | D3: Lecture
A4: S/P | B4: =SUMIF(Blocs!$B$2:$B$18,"S/P",Blocs!$P$2:$P$18) -> 29.807 | C4: =SUMIF(Blocs!$B$2:$B$18,"S/P",Blocs!$Q$2:$Q$18) -> 87.921
A5: Frais | B5: =SUMIF(Blocs!$B$2:$B$18,"Frais",Blocs!$P$2:$P$18) -> 47.073 | C5: =SUMIF(Blocs!$B$2:$B$18,"Frais",Blocs!$Q$2:$Q$18) -> 99.025
A6: Croissance | B6: =SUMIF(Blocs!$B$2:$B$18,"Croissance",Blocs!$P$2:$P$18) -> 2.97 | C6: =SUMIF(Blocs!$B$2:$B$18,"Croissance",Blocs!$Q$2:$Q$18) -> 8.17
A7: Capital | B7: =SUMIF(Blocs!$B$2:$B$18,"Capital",Blocs!$P$2:$P$18) -> 1.08 | C7: =SUMIF(Blocs!$B$2:$B$18,"Capital",Blocs!$Q$2:$Q$18) -> 3.24
A8: Total brut | B8: =SUM(B4:B7) -> 80.93 | C8: =SUM(C4:C7) -> 198.356
A9: En % des primes totales | B9: =B8/(Hypothèses!$B$5+Hypothèses!$B$6+Hypothèses!$B$7+Hypothèses!$B$8+Hypothèses!$B$9+Hypothèses!$B$10) -> 0.016186 | C9: =C8/(Hypothèses!$B$5+Hypothèses!$B$6+Hypothèses!$B$7+Hypothèses!$B$8+Hypothèses!$B$9+Hypothèses!$B$10) -> 0.0396712
A10: Coût de possession en croisière (fixe 2030 + variable) | B10: =SUM(Hypothèses!$E$58:$E$62)+Hypothèses!$B$63*B8 -> 27.093 | C10: =SUM(Hypothèses!$E$58:$E$62)+Hypothèses!$B$63*C8 -> 38.8356
A11: Valeur nette en croisière | B11: =B8-B10 -> 53.837 | C11: =C8-C10 -> 159.5204
A13: Par maillon (M€, bas / haut)
A14: Maillon | B14: Bas | C14: Haut
A15: Sinistres | B15: =SUMIF(Blocs!$C$2:$C$18,"Sinistres",Blocs!$P$2:$P$18) -> 26.823 | C15: =SUMIF(Blocs!$C$2:$C$18,"Sinistres",Blocs!$Q$2:$Q$18) -> 66.444
A16: Tarification | B16: =SUMIF(Blocs!$C$2:$C$18,"Tarification",Blocs!$P$2:$P$18) -> 7.5 | C16: =SUMIF(Blocs!$C$2:$C$18,"Tarification",Blocs!$Q$2:$Q$18) -> 25
A17: Souscription | B17: =SUMIF(Blocs!$C$2:$C$18,"Souscription",Blocs!$P$2:$P$18) -> 10.35 | C17: =SUMIF(Blocs!$C$2:$C$18,"Souscription",Blocs!$Q$2:$Q$18) -> 23.07
A18: Fraude | B18: =SUMIF(Blocs!$C$2:$C$18,"Fraude",Blocs!$P$2:$P$18) -> 8 | C18: =SUMIF(Blocs!$C$2:$C$18,"Fraude",Blocs!$Q$2:$Q$18) -> 20
A19: Support | B19: =SUMIF(Blocs!$C$2:$C$18,"Support",Blocs!$P$2:$P$18) -> 7.395 | C19: =SUMIF(Blocs!$C$2:$C$18,"Support",Blocs!$Q$2:$Q$18) -> 17.255
A20: Contrats | B20: =SUMIF(Blocs!$C$2:$C$18,"Contrats",Blocs!$P$2:$P$18) -> 9.368 | C20: =SUMIF(Blocs!$C$2:$C$18,"Contrats",Blocs!$Q$2:$Q$18) -> 16.68
A21: Distribution | B21: =SUMIF(Blocs!$C$2:$C$18,"Distribution",Blocs!$P$2:$P$18) -> 4.57 | C21: =SUMIF(Blocs!$C$2:$C$18,"Distribution",Blocs!$Q$2:$Q$18) -> 11.43
A22: Prévention | B22: =SUMIF(Blocs!$C$2:$C$18,"Prévention",Blocs!$P$2:$P$18) -> 2.784 | C22: =SUMIF(Blocs!$C$2:$C$18,"Prévention",Blocs!$Q$2:$Q$18) -> 8.352
A23: Actuariat | B23: =SUMIF(Blocs!$C$2:$C$18,"Actuariat",Blocs!$P$2:$P$18) -> 3.06 | C23: =SUMIF(Blocs!$C$2:$C$18,"Actuariat",Blocs!$Q$2:$Q$18) -> 6.885
A24: Capital | B24: =SUMIF(Blocs!$C$2:$C$18,"Capital",Blocs!$P$2:$P$18) -> 1.08 | C24: =SUMIF(Blocs!$C$2:$C$18,"Capital",Blocs!$Q$2:$Q$18) -> 3.24
A26: Ratio combiné non-vie (auto, habitation, santé, entreprises)
A27: Primes non-vie (M€) | B27: =Hypothèses!$B$5+Hypothèses!$B$6+Hypothèses!$B$7+Hypothèses!$B$10 -> 3100
A28: S/P non-vie | B28: =(Hypothèses!$B$5*Hypothèses!$B$13+Hypothèses!$B$6*Hypothèses!$B$14+Hypothèses!$B$7*Hypothèses!$B$15+Hypothèses!$B$10*Hypothèses!$B$17)/B27 -> 0.71129032
A29: Ratio de frais non-vie (commissions + frais internes au prorata des primes) | B29: =Hypothèses!$B$29+Hypothèses!$B$28*(B27/(Hypothèses!$B$5+Hypothèses!$B$6+Hypothèses!$B$7+Hypothèses!$B$8+Hypothèses!$B$9+Hypothèses!$B$10))/B27 -> 0.234
A30: Ratio combiné 2026 | B30: =B28+B29 -> 0.94529032
A31: Pont (points de ratio combiné) | B31: Bas | C31: Haut
A32: Gain S/P (blocs S/P / primes non-vie) | B32: =B4/B27 -> 0.0096151613 | C32: =C4/B27 -> 0.028361613
A33: Gain de frais (blocs frais × part non-vie / primes non-vie) | B33: =B5*(B27/(Hypothèses!$B$5+Hypothèses!$B$6+Hypothèses!$B$7+Hypothèses!$B$8+Hypothèses!$B$9+Hypothèses!$B$10))/B27 -> 0.0094146 | C33: =C5*(B27/(Hypothèses!$B$5+Hypothèses!$B$6+Hypothèses!$B$7+Hypothèses!$B$8+Hypothèses!$B$9+Hypothèses!$B$10))/B27 -> 0.019805
A34: Coût de possession (part non-vie / primes non-vie) | B34: =B10*(B27/(Hypothèses!$B$5+Hypothèses!$B$6+Hypothèses!$B$7+Hypothèses!$B$8+Hypothèses!$B$9+Hypothèses!$B$10))/B27 -> 0.0054186 | C34: =C10*(B27/(Hypothèses!$B$5+Hypothèses!$B$6+Hypothèses!$B$7+Hypothèses!$B$8+Hypothèses!$B$9+Hypothèses!$B$10))/B27 -> 0.00776712
A35: Ratio combiné cible | B35: =B30-B32-B33+B34 -> 0.93167916 | C35: =B30-C32-C33+C34 -> 0.90489083

Sheet Trajectoire
A1: Montée en charge 2027-2030 (M€) : valeur brute = résultat de croisière × part atteinte selon le type de montée en charge
A3: Bloc | B3: Type | C3: Bas 2027 | D3: Bas 2028 | E3: Bas 2029 | F3: Bas 2030 | G3: Haut 2027 | H3: Haut 2028 | I3: Haut 2029 | J3: Haut 2030
A4: =Blocs!A2 -> E1 | B4: =Blocs!L2 -> fast | C4: =Blocs!$P$2*INDEX(Hypothèses!$B$52:$B$55,MATCH($B4,Hypothèses!$F$52:$F$55,0)) -> 2.295 | D4: =Blocs!$P$2*INDEX(Hypothèses!$C$52:$C$55,MATCH($B4,Hypothèses!$F$52:$F$55,0)) -> 6.885 | E4: =Blocs!$P$2*INDEX(Hypothèses!$D$52:$D$55,MATCH($B4,Hypothèses!$F$52:$F$55,0)) -> 11.475 | F4: =Blocs!$P$2*INDEX(Hypothèses!$E$52:$E$55,MATCH($B4,Hypothèses!$F$52:$F$55,0)) -> 14.535 | G4: =Blocs!$Q$2*INDEX(Hypothèses!$B$52:$B$55,MATCH($B4,Hypothèses!$F$52:$F$55,0)) -> 4.78125 | H4: =Blocs!$Q$2*INDEX(Hypothèses!$C$52:$C$55,MATCH($B4,Hypothèses!$F$52:$F$55,0)) -> 14.34375 | I4: =Blocs!$Q$2*INDEX(Hypothèses!$D$52:$D$55,MATCH($B4,Hypothèses!$F$52:$F$55,0)) -> 23.90625 | J4: =Blocs!$Q$2*INDEX(Hypothèses!$E$52:$E$55,MATCH($B4,Hypothèses!$F$52:$F$55,0)) -> 30.28125
A5: =Blocs!A3 -> E2 | B5: =Blocs!L3 -> fast | C5: =Blocs!$P$3*INDEX(Hypothèses!$B$52:$B$55,MATCH($B5,Hypothèses!$F$52:$F$55,0)) -> 1.4025 | D5: =Blocs!$P$3*INDEX(Hypothèses!$C$52:$C$55,MATCH($B5,Hypothèses!$F$52:$F$55,0)) -> 4.2075 | E5: =Blocs!$P$3*INDEX(Hypothèses!$D$52:$D$55,MATCH($B5,Hypothèses!$F$52:$F$55,0)) -> 7.0125 | F5: =Blocs!$P$3*INDEX(Hypothèses!$E$52:$E$55,MATCH($B5,Hypothèses!$F$52:$F$55,0)) -> 8.8825 | G5: =Blocs!$Q$3*INDEX(Hypothèses!$B$52:$B$55,MATCH($B5,Hypothèses!$F$52:$F$55,0)) -> 3.0855 | H5: =Blocs!$Q$3*INDEX(Hypothèses!$C$52:$C$55,MATCH($B5,Hypothèses!$F$52:$F$55,0)) -> 9.2565 | I5: =Blocs!$Q$3*INDEX(Hypothèses!$D$52:$D$55,MATCH($B5,Hypothèses!$F$52:$F$55,0)) -> 15.4275 | J5: =Blocs!$Q$3*INDEX(Hypothèses!$E$52:$E$55,MATCH($B5,Hypothèses!$F$52:$F$55,0)) -> 19.5415
A6: =Blocs!A4 -> E3 | B6: =Blocs!L4 -> fast | C6: =Blocs!$P$4*INDEX(Hypothèses!$B$52:$B$55,MATCH($B6,Hypothèses!$F$52:$F$55,0)) -> 1.2852 | D6: =Blocs!$P$4*INDEX(Hypothèses!$C$52:$C$55,MATCH($B6,Hypothèses!$F$52:$F$55,0)) -> 3.8556 | E6: =Blocs!$P$4*INDEX(Hypothèses!$D$52:$D$55,MATCH($B6,Hypothèses!$F$52:$F$55,0)) -> 6.426 | F6: =Blocs!$P$4*INDEX(Hypothèses!$E$52:$E$55,MATCH($B6,Hypothèses!$F$52:$F$55,0)) -> 8.1396 | G6: =Blocs!$Q$4*INDEX(Hypothèses!$B$52:$B$55,MATCH($B6,Hypothèses!$F$52:$F$55,0)) -> 2.142 | H6: =Blocs!$Q$4*INDEX(Hypothèses!$C$52:$C$55,MATCH($B6,Hypothèses!$F$52:$F$55,0)) -> 6.426 | I6: =Blocs!$Q$4*INDEX(Hypothèses!$D$52:$D$55,MATCH($B6,Hypothèses!$F$52:$F$55,0)) -> 10.71 | J6: =Blocs!$Q$4*INDEX(Hypothèses!$E$52:$E$55,MATCH($B6,Hypothèses!$F$52:$F$55,0)) -> 13.566
A7: =Blocs!A5 -> E4 | B7: =Blocs!L5 -> fast | C7: =Blocs!$P$5*INDEX(Hypothèses!$B$52:$B$55,MATCH($B7,Hypothèses!$F$52:$F$55,0)) -> 0.51 | D7: =Blocs!$P$5*INDEX(Hypothèses!$C$52:$C$55,MATCH($B7,Hypothèses!$F$52:$F$55,0)) -> 1.53 | E7: =Blocs!$P$5*INDEX(Hypothèses!$D$52:$D$55,MATCH($B7,Hypothèses!$F$52:$F$55,0)) -> 2.55 | F7: =Blocs!$P$5*INDEX(Hypothèses!$E$52:$E$55,MATCH($B7,Hypothèses!$F$52:$F$55,0)) -> 3.23 | G7: =Blocs!$Q$5*INDEX(Hypothèses!$B$52:$B$55,MATCH($B7,Hypothèses!$F$52:$F$55,0)) -> 1.224 | H7: =Blocs!$Q$5*INDEX(Hypothèses!$C$52:$C$55,MATCH($B7,Hypothèses!$F$52:$F$55,0)) -> 3.672 | I7: =Blocs!$Q$5*INDEX(Hypothèses!$D$52:$D$55,MATCH($B7,Hypothèses!$F$52:$F$55,0)) -> 6.12 | J7: =Blocs!$Q$5*INDEX(Hypothèses!$E$52:$E$55,MATCH($B7,Hypothèses!$F$52:$F$55,0)) -> 7.752
A8: =Blocs!A6 -> E5 | B8: =Blocs!L6 -> fast | C8: =Blocs!$P$6*INDEX(Hypothèses!$B$52:$B$55,MATCH($B8,Hypothèses!$F$52:$F$55,0)) -> 0.459 | D8: =Blocs!$P$6*INDEX(Hypothèses!$C$52:$C$55,MATCH($B8,Hypothèses!$F$52:$F$55,0)) -> 1.377 | E8: =Blocs!$P$6*INDEX(Hypothèses!$D$52:$D$55,MATCH($B8,Hypothèses!$F$52:$F$55,0)) -> 2.295 | F8: =Blocs!$P$6*INDEX(Hypothèses!$E$52:$E$55,MATCH($B8,Hypothèses!$F$52:$F$55,0)) -> 2.907 | G8: =Blocs!$Q$6*INDEX(Hypothèses!$B$52:$B$55,MATCH($B8,Hypothèses!$F$52:$F$55,0)) -> 1.03275 | H8: =Blocs!$Q$6*INDEX(Hypothèses!$C$52:$C$55,MATCH($B8,Hypothèses!$F$52:$F$55,0)) -> 3.09825 | I8: =Blocs!$Q$6*INDEX(Hypothèses!$D$52:$D$55,MATCH($B8,Hypothèses!$F$52:$F$55,0)) -> 5.16375 | J8: =Blocs!$Q$6*INDEX(Hypothèses!$E$52:$E$55,MATCH($B8,Hypothèses!$F$52:$F$55,0)) -> 6.54075
A9: =Blocs!A7 -> E6 | B9: =Blocs!L7 -> fast | C9: =Blocs!$P$7*INDEX(Hypothèses!$B$52:$B$55,MATCH($B9,Hypothèses!$F$52:$F$55,0)) -> 1.10925 | D9: =Blocs!$P$7*INDEX(Hypothèses!$C$52:$C$55,MATCH($B9,Hypothèses!$F$52:$F$55,0)) -> 3.32775 | E9: =Blocs!$P$7*INDEX(Hypothèses!$D$52:$D$55,MATCH($B9,Hypothèses!$F$52:$F$55,0)) -> 5.54625 | F9: =Blocs!$P$7*INDEX(Hypothèses!$E$52:$E$55,MATCH($B9,Hypothèses!$F$52:$F$55,0)) -> 7.02525 | G9: =Blocs!$Q$7*INDEX(Hypothèses!$B$52:$B$55,MATCH($B9,Hypothèses!$F$52:$F$55,0)) -> 2.58825 | H9: =Blocs!$Q$7*INDEX(Hypothèses!$C$52:$C$55,MATCH($B9,Hypothèses!$F$52:$F$55,0)) -> 7.76475 | I9: =Blocs!$Q$7*INDEX(Hypothèses!$D$52:$D$55,MATCH($B9,Hypothèses!$F$52:$F$55,0)) -> 12.94125 | J9: =Blocs!$Q$7*INDEX(Hypothèses!$E$52:$E$55,MATCH($B9,Hypothèses!$F$52:$F$55,0)) -> 16.39225
A10: =Blocs!A8 -> L1 | B10: =Blocs!L8 -> lag | C10: =Blocs!$P$8*INDEX(Hypothèses!$B$52:$B$55,MATCH($B10,Hypothèses!$F$52:$F$55,0)) -> 0.4 | D10: =Blocs!$P$8*INDEX(Hypothèses!$C$52:$C$55,MATCH($B10,Hypothèses!$F$52:$F$55,0)) -> 2 | E10: =Blocs!$P$8*INDEX(Hypothèses!$D$52:$D$55,MATCH($B10,Hypothèses!$F$52:$F$55,0)) -> 4.4 | F10: =Blocs!$P$8*INDEX(Hypothèses!$E$52:$E$55,MATCH($B10,Hypothèses!$F$52:$F$55,0)) -> 6.8 | G10: =Blocs!$Q$8*INDEX(Hypothèses!$B$52:$B$55,MATCH($B10,Hypothèses!$F$52:$F$55,0)) -> 1 | H10: =Blocs!$Q$8*INDEX(Hypothèses!$C$52:$C$55,MATCH($B10,Hypothèses!$F$52:$F$55,0)) -> 5 | I10: =Blocs!$Q$8*INDEX(Hypothèses!$D$52:$D$55,MATCH($B10,Hypothèses!$F$52:$F$55,0)) -> 11 | J10: =Blocs!$Q$8*INDEX(Hypothèses!$E$52:$E$55,MATCH($B10,Hypothèses!$F$52:$F$55,0)) -> 17
A11: =Blocs!A9 -> L2 | B11: =Blocs!L9 -> lag | C11: =Blocs!$P$9*INDEX(Hypothèses!$B$52:$B$55,MATCH($B11,Hypothèses!$F$52:$F$55,0)) -> 0.3414 | D11: =Blocs!$P$9*INDEX(Hypothèses!$C$52:$C$55,MATCH($B11,Hypothèses!$F$52:$F$55,0)) -> 1.707 | E11: =Blocs!$P$9*INDEX(Hypothèses!$D$52:$D$55,MATCH($B11,Hypothèses!$F$52:$F$55,0)) -> 3.7554 | F11: =Blocs!$P$9*INDEX(Hypothèses!$E$52:$E$55,MATCH($B11,Hypothèses!$F$52:$F$55,0)) -> 5.8038 | G11: =Blocs!$Q$9*INDEX(Hypothèses!$B$52:$B$55,MATCH($B11,Hypothèses!$F$52:$F$55,0)) -> 1.0242 | H11: =Blocs!$Q$9*INDEX(Hypothèses!$C$52:$C$55,MATCH($B11,Hypothèses!$F$52:$F$55,0)) -> 5.121 | I11: =Blocs!$Q$9*INDEX(Hypothèses!$D$52:$D$55,MATCH($B11,Hypothèses!$F$52:$F$55,0)) -> 11.2662 | J11: =Blocs!$Q$9*INDEX(Hypothèses!$E$52:$E$55,MATCH($B11,Hypothèses!$F$52:$F$55,0)) -> 17.4114
A12: =Blocs!A10 -> L3 | B12: =Blocs!L10 -> lag | C12: =Blocs!$P$10*INDEX(Hypothèses!$B$52:$B$55,MATCH($B12,Hypothèses!$F$52:$F$55,0)) -> 0.1245 | D12: =Blocs!$P$10*INDEX(Hypothèses!$C$52:$C$55,MATCH($B12,Hypothèses!$F$52:$F$55,0)) -> 0.6225 | E12: =Blocs!$P$10*INDEX(Hypothèses!$D$52:$D$55,MATCH($B12,Hypothèses!$F$52:$F$55,0)) -> 1.3695 | F12: =Blocs!$P$10*INDEX(Hypothèses!$E$52:$E$55,MATCH($B12,Hypothèses!$F$52:$F$55,0)) -> 2.1165 | G12: =Blocs!$Q$10*INDEX(Hypothèses!$B$52:$B$55,MATCH($B12,Hypothèses!$F$52:$F$55,0)) -> 0.3735 | H12: =Blocs!$Q$10*INDEX(Hypothèses!$C$52:$C$55,MATCH($B12,Hypothèses!$F$52:$F$55,0)) -> 1.8675 | I12: =Blocs!$Q$10*INDEX(Hypothèses!$D$52:$D$55,MATCH($B12,Hypothèses!$F$52:$F$55,0)) -> 4.1085 | J12: =Blocs!$Q$10*INDEX(Hypothèses!$E$52:$E$55,MATCH($B12,Hypothèses!$F$52:$F$55,0)) -> 6.3495
A13: =Blocs!A11 -> L4 | B13: =Blocs!L11 -> lag | C13: =Blocs!$P$11*INDEX(Hypothèses!$B$52:$B$55,MATCH($B13,Hypothèses!$F$52:$F$55,0)) -> 0.375 | D13: =Blocs!$P$11*INDEX(Hypothèses!$C$52:$C$55,MATCH($B13,Hypothèses!$F$52:$F$55,0)) -> 1.875 | E13: =Blocs!$P$11*INDEX(Hypothèses!$D$52:$D$55,MATCH($B13,Hypothèses!$F$52:$F$55,0)) -> 4.125 | F13: =Blocs!$P$11*INDEX(Hypothèses!$E$52:$E$55,MATCH($B13,Hypothèses!$F$52:$F$55,0)) -> 6.375 | G13: =Blocs!$Q$11*INDEX(Hypothèses!$B$52:$B$55,MATCH($B13,Hypothèses!$F$52:$F$55,0)) -> 1.25 | H13: =Blocs!$Q$11*INDEX(Hypothèses!$C$52:$C$55,MATCH($B13,Hypothèses!$F$52:$F$55,0)) -> 6.25 | I13: =Blocs!$Q$11*INDEX(Hypothèses!$D$52:$D$55,MATCH($B13,Hypothèses!$F$52:$F$55,0)) -> 13.75 | J13: =Blocs!$Q$11*INDEX(Hypothèses!$E$52:$E$55,MATCH($B13,Hypothèses!$F$52:$F$55,0)) -> 21.25
A14: =Blocs!A12 -> L5 | B14: =Blocs!L12 -> lag | C14: =Blocs!$P$12*INDEX(Hypothèses!$B$52:$B$55,MATCH($B14,Hypothèses!$F$52:$F$55,0)) -> 0.1392 | D14: =Blocs!$P$12*INDEX(Hypothèses!$C$52:$C$55,MATCH($B14,Hypothèses!$F$52:$F$55,0)) -> 0.696 | E14: =Blocs!$P$12*INDEX(Hypothèses!$D$52:$D$55,MATCH($B14,Hypothèses!$F$52:$F$55,0)) -> 1.5312 | F14: =Blocs!$P$12*INDEX(Hypothèses!$E$52:$E$55,MATCH($B14,Hypothèses!$F$52:$F$55,0)) -> 2.3664 | G14: =Blocs!$Q$12*INDEX(Hypothèses!$B$52:$B$55,MATCH($B14,Hypothèses!$F$52:$F$55,0)) -> 0.4176 | H14: =Blocs!$Q$12*INDEX(Hypothèses!$C$52:$C$55,MATCH($B14,Hypothèses!$F$52:$F$55,0)) -> 2.088 | I14: =Blocs!$Q$12*INDEX(Hypothèses!$D$52:$D$55,MATCH($B14,Hypothèses!$F$52:$F$55,0)) -> 4.5936 | J14: =Blocs!$Q$12*INDEX(Hypothèses!$E$52:$E$55,MATCH($B14,Hypothèses!$F$52:$F$55,0)) -> 7.0992
A15: =Blocs!A13 -> L6 | B15: =Blocs!L13 -> lag | C15: =Blocs!$P$13*INDEX(Hypothèses!$B$52:$B$55,MATCH($B15,Hypothèses!$F$52:$F$55,0)) -> 0.11025 | D15: =Blocs!$P$13*INDEX(Hypothèses!$C$52:$C$55,MATCH($B15,Hypothèses!$F$52:$F$55,0)) -> 0.55125 | E15: =Blocs!$P$13*INDEX(Hypothèses!$D$52:$D$55,MATCH($B15,Hypothèses!$F$52:$F$55,0)) -> 1.21275 | F15: =Blocs!$P$13*INDEX(Hypothèses!$E$52:$E$55,MATCH($B15,Hypothèses!$F$52:$F$55,0)) -> 1.87425 | G15: =Blocs!$Q$13*INDEX(Hypothèses!$B$52:$B$55,MATCH($B15,Hypothèses!$F$52:$F$55,0)) -> 0.33075 | H15: =Blocs!$Q$13*INDEX(Hypothèses!$C$52:$C$55,MATCH($B15,Hypothèses!$F$52:$F$55,0)) -> 1.65375 | I15: =Blocs!$Q$13*INDEX(Hypothèses!$D$52:$D$55,MATCH($B15,Hypothèses!$F$52:$F$55,0)) -> 3.63825 | J15: =Blocs!$Q$13*INDEX(Hypothèses!$E$52:$E$55,MATCH($B15,Hypothèses!$F$52:$F$55,0)) -> 5.62275
A16: =Blocs!A14 -> G1 | B16: =Blocs!L14 -> mid | C16: =Blocs!$P$14*INDEX(Hypothèses!$B$52:$B$55,MATCH($B16,Hypothèses!$F$52:$F$55,0)) -> 0.08 | D16: =Blocs!$P$14*INDEX(Hypothèses!$C$52:$C$55,MATCH($B16,Hypothèses!$F$52:$F$55,0)) -> 0.28 | E16: =Blocs!$P$14*INDEX(Hypothèses!$D$52:$D$55,MATCH($B16,Hypothèses!$F$52:$F$55,0)) -> 0.52 | F16: =Blocs!$P$14*INDEX(Hypothèses!$E$52:$E$55,MATCH($B16,Hypothèses!$F$52:$F$55,0)) -> 0.72 | G16: =Blocs!$Q$14*INDEX(Hypothèses!$B$52:$B$55,MATCH($B16,Hypothèses!$F$52:$F$55,0)) -> 0.24 | H16: =Blocs!$Q$14*INDEX(Hypothèses!$C$52:$C$55,MATCH($B16,Hypothèses!$F$52:$F$55,0)) -> 0.84 | I16: =Blocs!$Q$14*INDEX(Hypothèses!$D$52:$D$55,MATCH($B16,Hypothèses!$F$52:$F$55,0)) -> 1.56 | J16: =Blocs!$Q$14*INDEX(Hypothèses!$E$52:$E$55,MATCH($B16,Hypothèses!$F$52:$F$55,0)) -> 2.16
A17: =Blocs!A15 -> G2 | B17: =Blocs!L15 -> mid | C17: =Blocs!$P$15*INDEX(Hypothèses!$B$52:$B$55,MATCH($B17,Hypothèses!$F$52:$F$55,0)) -> 0.072 | D17: =Blocs!$P$15*INDEX(Hypothèses!$C$52:$C$55,MATCH($B17,Hypothèses!$F$52:$F$55,0)) -> 0.252 | E17: =Blocs!$P$15*INDEX(Hypothèses!$D$52:$D$55,MATCH($B17,Hypothèses!$F$52:$F$55,0)) -> 0.468 | F17: =Blocs!$P$15*INDEX(Hypothèses!$E$52:$E$55,MATCH($B17,Hypothèses!$F$52:$F$55,0)) -> 0.648 | G17: =Blocs!$Q$15*INDEX(Hypothèses!$B$52:$B$55,MATCH($B17,Hypothèses!$F$52:$F$55,0)) -> 0.192 | H17: =Blocs!$Q$15*INDEX(Hypothèses!$C$52:$C$55,MATCH($B17,Hypothèses!$F$52:$F$55,0)) -> 0.672 | I17: =Blocs!$Q$15*INDEX(Hypothèses!$D$52:$D$55,MATCH($B17,Hypothèses!$F$52:$F$55,0)) -> 1.248 | J17: =Blocs!$Q$15*INDEX(Hypothèses!$E$52:$E$55,MATCH($B17,Hypothèses!$F$52:$F$55,0)) -> 1.728
A18: =Blocs!A16 -> G3 | B18: =Blocs!L16 -> mid | C18: =Blocs!$P$16*INDEX(Hypothèses!$B$52:$B$55,MATCH($B18,Hypothèses!$F$52:$F$55,0)) -> 0.1 | D18: =Blocs!$P$16*INDEX(Hypothèses!$C$52:$C$55,MATCH($B18,Hypothèses!$F$52:$F$55,0)) -> 0.35 | E18: =Blocs!$P$16*INDEX(Hypothèses!$D$52:$D$55,MATCH($B18,Hypothèses!$F$52:$F$55,0)) -> 0.65 | F18: =Blocs!$P$16*INDEX(Hypothèses!$E$52:$E$55,MATCH($B18,Hypothèses!$F$52:$F$55,0)) -> 0.9 | G18: =Blocs!$Q$16*INDEX(Hypothèses!$B$52:$B$55,MATCH($B18,Hypothèses!$F$52:$F$55,0)) -> 0.25 | H18: =Blocs!$Q$16*INDEX(Hypothèses!$C$52:$C$55,MATCH($B18,Hypothèses!$F$52:$F$55,0)) -> 0.875 | I18: =Blocs!$Q$16*INDEX(Hypothèses!$D$52:$D$55,MATCH($B18,Hypothèses!$F$52:$F$55,0)) -> 1.625 | J18: =Blocs!$Q$16*INDEX(Hypothèses!$E$52:$E$55,MATCH($B18,Hypothèses!$F$52:$F$55,0)) -> 2.25
A19: =Blocs!A17 -> G4 | B19: =Blocs!L17 -> mid | C19: =Blocs!$P$17*INDEX(Hypothèses!$B$52:$B$55,MATCH($B19,Hypothèses!$F$52:$F$55,0)) -> 0.045 | D19: =Blocs!$P$17*INDEX(Hypothèses!$C$52:$C$55,MATCH($B19,Hypothèses!$F$52:$F$55,0)) -> 0.1575 | E19: =Blocs!$P$17*INDEX(Hypothèses!$D$52:$D$55,MATCH($B19,Hypothèses!$F$52:$F$55,0)) -> 0.2925 | F19: =Blocs!$P$17*INDEX(Hypothèses!$E$52:$E$55,MATCH($B19,Hypothèses!$F$52:$F$55,0)) -> 0.405 | G19: =Blocs!$Q$17*INDEX(Hypothèses!$B$52:$B$55,MATCH($B19,Hypothèses!$F$52:$F$55,0)) -> 0.135 | H19: =Blocs!$Q$17*INDEX(Hypothèses!$C$52:$C$55,MATCH($B19,Hypothèses!$F$52:$F$55,0)) -> 0.4725 | I19: =Blocs!$Q$17*INDEX(Hypothèses!$D$52:$D$55,MATCH($B19,Hypothèses!$F$52:$F$55,0)) -> 0.8775 | J19: =Blocs!$Q$17*INDEX(Hypothèses!$E$52:$E$55,MATCH($B19,Hypothèses!$F$52:$F$55,0)) -> 1.215
A20: =Blocs!A18 -> C1 | B20: =Blocs!L18 -> slow | C20: =Blocs!$P$18*INDEX(Hypothèses!$B$52:$B$55,MATCH($B20,Hypothèses!$F$52:$F$55,0)) -> 0 | D20: =Blocs!$P$18*INDEX(Hypothèses!$C$52:$C$55,MATCH($B20,Hypothèses!$F$52:$F$55,0)) -> 0.216 | E20: =Blocs!$P$18*INDEX(Hypothèses!$D$52:$D$55,MATCH($B20,Hypothèses!$F$52:$F$55,0)) -> 0.54 | F20: =Blocs!$P$18*INDEX(Hypothèses!$E$52:$E$55,MATCH($B20,Hypothèses!$F$52:$F$55,0)) -> 0.864 | G20: =Blocs!$Q$18*INDEX(Hypothèses!$B$52:$B$55,MATCH($B20,Hypothèses!$F$52:$F$55,0)) -> 0 | H20: =Blocs!$Q$18*INDEX(Hypothèses!$C$52:$C$55,MATCH($B20,Hypothèses!$F$52:$F$55,0)) -> 0.648 | I20: =Blocs!$Q$18*INDEX(Hypothèses!$D$52:$D$55,MATCH($B20,Hypothèses!$F$52:$F$55,0)) -> 1.62 | J20: =Blocs!$Q$18*INDEX(Hypothèses!$E$52:$E$55,MATCH($B20,Hypothèses!$F$52:$F$55,0)) -> 2.592
A22: Valeur brute | C22: =SUM(C4:C20) -> 8.8483 | D22: =SUM(D4:D20) -> 29.8901 | E22: =SUM(E4:E20) -> 54.1691 | F22: =SUM(F4:F20) -> 73.5923 | G22: =SUM(G4:G20) -> 20.0668 | H22: =SUM(H4:H20) -> 70.049 | I22: =SUM(I4:I20) -> 129.5558 | J22: =SUM(J4:J20) -> 178.7516
A23: Coût fixe | C23: =SUM(Hypothèses!$B$58:$B$62) -> 25 | D23: =SUM(Hypothèses!$C$58:$C$62) -> 25 | E23: =SUM(Hypothèses!$D$58:$D$62) -> 22 | F23: =SUM(Hypothèses!$E$58:$E$62) -> 19 | G23: =SUM(Hypothèses!$B$58:$B$62) -> 25 | H23: =SUM(Hypothèses!$C$58:$C$62) -> 25 | I23: =SUM(Hypothèses!$D$58:$D$62) -> 22 | J23: =SUM(Hypothèses!$E$58:$E$62) -> 19
A24: Coût variable | C24: =Hypothèses!$B$63*C22 -> 0.88483 | D24: =Hypothèses!$B$63*D22 -> 2.98901 | E24: =Hypothèses!$B$63*E22 -> 5.41691 | F24: =Hypothèses!$B$63*F22 -> 7.35923 | G24: =Hypothèses!$B$63*G22 -> 2.00668 | H24: =Hypothèses!$B$63*H22 -> 7.0049 | I24: =Hypothèses!$B$63*I22 -> 12.95558 | J24: =Hypothèses!$B$63*J22 -> 17.87516
A25: Coût de possession | C25: =C23+C24 -> 25.88483 | D25: =D23+D24 -> 27.98901 | E25: =E23+E24 -> 27.41691 | F25: =F23+F24 -> 26.35923 | G25: =G23+G24 -> 27.00668 | H25: =H23+H24 -> 32.0049 | I25: =I23+I24 -> 34.95558 | J25: =J23+J24 -> 36.87516
A26: Valeur nette | C26: =C22-C25 -> -17.03653 | D26: =D22-D25 -> 1.90109 | E26: =E22-E25 -> 26.75219 | F26: =F22-F25 -> 47.23307 | G26: =G22-G25 -> -6.93988 | H26: =H22-H25 -> 38.0441 | I26: =I22-I25 -> 94.60022 | J26: =J22-J25 -> 141.87644
A27: Valeur nette cumulée | C27: =C26 -> -17.03653 | D27: =C27+D26 -> -15.13544 | E27: =D27+E26 -> 11.61675 | F27: =E27+F26 -> 58.84982 | G27: =G26 -> -6.93988 | H27: =G27+H26 -> 31.10422 | I27: =H27+I26 -> 125.70444 | J27: =I27+J26 -> 267.58088
A29: Point mort (première année de cumul positif) | B29: bas → | C29: =IFERROR(INDEX({2027,2028,2029,2030},MATCH(TRUE(),INDEX(C27:F27>0,0),0)),"au-delà de 2030") -> 2029 | F29: haut → | G29: =IFERROR(INDEX({2027,2028,2029,2030},MATCH(TRUE(),INDEX(G27:J27>0,0),0)),"au-delà de 2030") -> 2028

Sheet Sensibilités
A1: Sensibilités de la valeur nette annuelle de croisière (M€), une hypothèse à la fois
A3: Cas médian : valeur brute = moyenne bas/haut ; coût = fixe 2030 + variable
A4: Valeur brute médiane | B4: =(Résultats!B8+Résultats!C8)/2 -> 139.643
A5: Blocs frais, médiane | B5: =(Résultats!B5+Résultats!C5)/2 -> 73.049
A6: Blocs S/P, médiane | B6: =(Résultats!B4+Résultats!C4)/2 -> 58.864
A7: Coût fixe 2030 | B7: =SUM(Hypothèses!$E$58:$E$62) -> 19
A8: Valeur nette médiane | B8: =B4-B7-Hypothèses!$B$63*B4 -> 106.6787
A10: Hypothèse testée | B10: Dégradé | C10: Amélioré | D10: Définition
A11: Adoption effective −30 % / +30 % | B11: =B4*0.7-B7-Hypothèses!$B$63*B4*0.7 -> 68.97509 | C11: =B4*1.3-B7-Hypothèses!$B$63*B4*1.3 -> 144.38231 | D11: Toute la valeur brute × 0,7 ou × 1,3
A12: Capacité libérée réalisée à 50 % / 100 % (choix RH) | B12: =(B4-0.5*B5)-B7-Hypothèses!$B$63*(B4-0.5*B5) -> 73.80665 | C12: =B8 -> 106.6787 | D12: Moitié des blocs frais non convertie en économie
A13: Effets S/P : borne basse / borne haute | B13: =B8-(Résultats!C4-Résultats!B4)/2 -> 77.6217 | C13: =B8+(Résultats!C4-Résultats!B4)/2 -> 135.7357 | D13: Écart au médian des blocs S/P (hors effet sur le coût variable)
A14: Coût de possession fixe +40 % / −20 % | B14: =B4-B7*1.4-Hypothèses!$B$63*B4 -> 99.0787 | C14: =B4-B7*0.8-Hypothèses!$B$63*B4 -> 110.4787 | D14: Coût fixe × 1,4 ou × 0,8
A15: Effets frais : borne basse / borne haute | B15: =B8-(Résultats!C5-Résultats!B5)/2 -> 80.7027 | C15: =B8+(Résultats!C5-Résultats!B5)/2 -> 132.6547 | D15: Écart au médian des blocs frais (hors effet sur le coût variable)

Sheet Cockpit
A1: Indicateur tangible | B1: Référence 2026 | C1: Cible 2028 | D1: Cible 2030 | E1: Propriétaire | F1: Bloc
A2: Traitement automatique des sinistres simples | B2: 8 % | C2: 25 % | D2: 45 % | E2: Dir. sinistres | F2: E1
A3: Délai de règlement d'un sinistre simple (jours) | B3: 12 | C3: 7 | D3: 4 | E3: Dir. sinistres | F3: E1
A4: Délai de cotation entreprises (jours ouvrés) | B4: 3 | C4: 1 | D4: < 0,5 | E4: Dir. souscription | F4: E2 · G3
A5: Approbation automatique prévoyance-vie (éligibles) | B5: 30 % | C5: 45 % | D5: 60 % | E5: Dir. souscription | F5: E2
A6: Résolution automatique des contacts simples | B6: 10 % | C6: 25 % | D6: 40 % | E6: Relation client | F6: E3
A7: Fraude évitée (M€ par an) | B7: 20 | C7: 26 | D7: 32 – 40 | E7: Dir. fraude | F7: L1
A8: Fuite de valeur sinistres dommages (échantillon) | B8: mesure T0 | C8: −0,4 pt | D8: −0,8 pt | E8: Contrôle technique | F8: L2
A9: Rétention auto et habitation | B9: 87,0 % | C9: 87,5 % | D9: 88,0 % | E9: Dir. marketing | F9: G1
A10: Délai de clôture trimestrielle (jours ouvrés) | B10: 25 | C10: 18 | D10: 12 | E10: Dir. financière | F10: E5
A11: Coût IA par transaction (€ par dossier) | B11: n/a | C11: mesuré | D11: en baisse | E11: DSI | F11: TCO
A12: Annulation en appel des refus de prestation | B12: mesure T0 | C12: stable | D12: stable | E12: Conformité | F12: garde-fou
A13: Systèmes d'IA inventoriés et classés (AI Act) | B13: 40 % | C13: 100 % | D13: 100 % | E13: Risques | F13: garde-fou
A15: Cibles indicatives de l'assureur type, à recalibrer sur la mesure T0 réelle ; un propriétaire unique par indicateur ; les deux garde-fous ne doivent jamais se dégrader.

Sheet Catalogue
A1: Cas | B1: Maillon | C1: Famille | D1: Horizon | E1: Autonomie | F1: Classe AI Act | G1: Valeur /5 | H1: Faisabilité /5 | I1: Intitulé | J1: Socles | K1: Leviers | L1: Fiches benchmark
A2: STR-01 | B2: Stratégie | C2: Génératif | D2: H1 | E2: L2 | F2: Minimal | G2: 3 | H2: 4 | I2: Veille concurrentielle et réglementaire augmentée | J2: kb, doc | K2: gr, risk | L2: evident-2026
A3: STR-02 | B3: Stratégie | C3: Jumeau | D3: H2 | E3: L2 | F3: Minimal | G3: 4 | H3: 3 | I3: Conception produit assistée et test de concept simulé | J3: sim, kb, price | K3: gr
A4: STR-03 | B4: Stratégie | C4: ML prédictif | D4: H2 | E4: L1 | F4: Minimal | G4: 4 | H4: 3 | I4: Détection des déficits de protection et des risques émergents | J4: ext, geo | K4: gr | L4: ia-humain
A5: STR-04 | B5: Stratégie | C5: Génératif | D5: H1 | E5: L2 | F5: Minimal | G5: 3 | H5: 4 | I5: Rédaction et contrôle des conditions générales | J5: doc, kb | K5: risk, gr
A6: STR-05 | B6: Stratégie | C6: Jumeau | D6: H2 | E6: L2 | F6: Minimal | G6: 5 | H6: 2 | I6: Jumeau numérique du portefeuille pour l'arbitrage stratégique | J6: sim, price | K6: gr, cap
A7: STR-06 | B7: Stratégie | C7: Optimisation / quantique | D7: H2 | E7: L2 | F7: Minimal | G7: 5 | H7: 3 | I7: Allocation de capacité et pilotage du mix par segment | J7: opt, sim | K7: gr, cap, lr | L7: allstate-ibm-quantum
A8: STR-07 | B8: Stratégie | C8: ML prédictif | D8: H2 | E8: L2 | F8: Minimal | G8: 4 | H8: 3 | I8: Conception de produits paramétriques et embarqués | J8: geo, ext, sim | K8: gr, lr
A9: PRC-01 | B9: Tarification | C9: ML prédictif | D9: H1 | E9: L2 | F9: Minimal | G9: 5 | H9: 4 | I9: Prime pure par machine learning interprétable | J9: price, mrm | K9: lr, gr
A10: PRC-02 | B10: Tarification | C10: ML prédictif | D10: H1 | E10: L2 | F10: Haut risque | G10: 4 | H10: 3 | I10: Tarification santé et prévoyance des personnes physiques | J10: price, mrm | K10: lr, risk | L10: acpr-fairness, eiopa-opinion
A11: PRC-03 | B11: Tarification | C11: Optimisation / quantique | D11: H1 | E11: L2 | F11: Minimal | G11: 5 | H11: 3 | I11: Optimisation tarifaire sous contraintes | J11: price, opt, mrm | K11: gr, lr, risk
A12: PRC-04 | B12: Tarification | C12: Agentique | D12: H2 | E12: L3 | F12: Minimal | G12: 4 | H12: 3 | I12: Agent de révision tarifaire | J12: price, orch, mrm | K12: lr, er, gr
A13: PRC-05 | B13: Tarification | C13: ML prédictif | D13: H1 | E13: L2 | F13: Minimal | G13: 4 | H13: 4 | I13: Zonier géo-climatique enrichi | J13: geo, price | K13: lr
A14: PRC-06 | B14: Tarification | C14: ML prédictif | D14: H1 | E14: L2 | F14: Minimal | G14: 3 | H14: 3 | I14: Tarification à l'usage et télématique | J14: ext, price | K14: lr, gr
A15: PRC-07 | B15: Tarification | C15: ML prédictif | D15: H1 | E15: L2 | F15: Minimal | G15: 4 | H15: 3 | I15: Tarification des risques professionnels par données externes | J15: price, ext, doc | K15: lr, gr
A16: PRC-08 | B16: Tarification | C16: ML prédictif | D16: H1 | E16: L2 | F16: Minimal | G16: 4 | H16: 3 | I16: Tarification cyber par analyse de la surface d'attaque | J16: ext, price | K16: lr
A17: PRC-09 | B17: Tarification | C17: Agentique | D17: H1 | E17: L3 | F17: Minimal | G17: 4 | H17: 4 | I17: Surveillance continue des modèles tarifaires | J17: mrm, orch | K17: lr, risk
A18: PRC-10 | B18: Tarification | C18: ML prédictif | D18: H1 | E18: L2 | F18: Minimal | G18: 3 | H18: 4 | I18: Tests d'équité et de discrimination indirecte | J18: mrm, price | K18: risk | L18: acpr-fairness
A19: PRC-11 | B19: Tarification | C19: Génératif | D19: H1 | E19: L2 | F19: Minimal | G19: 3 | H19: 5 | I19: Copilote de l'actuaire tarification | J19: code, kb | K19: er, cx
A20: PRC-12 | B20: Tarification | C20: Jumeau | D20: H2 | E20: L2 | F20: Minimal | G20: 5 | H20: 2 | I20: Jumeau numérique de la tarification | J20: sim, price, opt | K20: gr, lr
A21: PRC-13 | B21: Tarification | C21: ML prédictif | D21: H1 | E21: L2 | F21: Minimal | G21: 4 | H21: 3 | I21: Études d'expérience vie et santé augmentées | J21: price, mrm | K21: lr, cap
A22: PRC-14 | B22: Tarification | C22: ML prédictif | D22: H1 | E22: L2 | F22: Minimal | G22: 4 | H22: 3 | I22: Modélisation du comportement des assurés vie | J22: price, sim | K22: cap, gr
A23: DST-01 | B23: Distribution | C23: ML prédictif | D23: H1 | E23: L2 | F23: Minimal | G23: 4 | H23: 4 | I23: Prochaine meilleure offre multi-produits | J23: c360 | K23: gr
A24: DST-02 | B24: Distribution | C24: ML prédictif | D24: H1 | E24: L3 | F24: Minimal | G24: 4 | H24: 4 | I24: Prédiction de l'attrition et rétention proactive | J24: c360, orch | K24: gr, cx
A25: DST-03 | B25: Distribution | C25: Génératif | D25: H1 | E25: L2 | F25: Minimal | G25: 4 | H25: 4 | I25: Copilote du conseiller et de l'agent général | J25: c360, kb | K25: gr, cx, er
A26: DST-04 | B26: Distribution | C26: Agentique | D26: H1 | E26: L3 | F26: Transparence | G26: 4 | H26: 4 | I26: Agent conversationnel de devis et de souscription | J26: conv, price, orch | K26: gr, er
A27: DST-05 | B27: Distribution | C27: Génératif | D27: H1 | E27: L2 | F27: Transparence | G27: 3 | H27: 5 | I27: Contenus marketing personnalisés sous contrôle conformité | J27: kb | K27: gr, er
A28: DST-06 | B28: Distribution | C28: Génératif | D28: H1 | E28: L3 | F28: Minimal | G28: 3 | H28: 4 | I28: Contrôle du devoir de conseil | J28: doc, kb | K28: risk
A29: DST-07 | B29: Distribution | C29: Optimisation / quantique | D29: H1 | E29: L2 | F29: Minimal | G29: 3 | H29: 4 | I29: Optimisation du mix média et du coût d'acquisition | J29: opt, c360 | K29: gr, er
A30: DST-08 | B30: Distribution | C30: Agentique | D30: H2 | E30: L3 | F30: Transparence | G30: 4 | H30: 3 | I30: Assurance embarquée chez les partenaires | J30: orch, price, c360 | K30: gr, er
... A32: DST-10 | B32: Distribution | C32: Agentique | D32: H3 | E32: L3 | F32: Transparence | G32: 4 | H32: 2 | I32: Dialogue entre agents de l'assureur et agents des clients | J32: orch, conv | K32: gr, cx
A33: UW-01 | B33: Souscription | C33: Génératif | D33: H1 | E33: L3 | F33: Minimal | G33: 5 | H33: 4 | I33: Ingestion des soumissions courtiers | J33: doc, orch | K33: gr, er | L33: hiscox-google
A34: UW-02 | B34: Souscription | C34: ML prédictif | D34: H1 | E34: L3 | F34: Minimal | G34: 4 | H34: 4 | I34: Tri et priorisation des soumissions | J34: price, doc | K34: gr, lr
A35: UW-03 | B35: Souscription | C35: Génératif | D35: H1 | E35: L2 | F35: Minimal | G35: 4 | H35: 4 | I35: Copilote du souscripteur grands risques | J35: kb, doc | K35: lr, gr | L35: qbe-accenture, swissre-scout, scor-ai
A36: UW-04 | B36: Souscription | C36: Agentique | D36: H1 | E36: L3 | F36: Haut risque | G36: 4 | H36: 3 | I36: Sélection médicale automatisée en prévoyance et emprunteur | J36: orch, doc, mrm | K36: gr, er, risk | L36: pingan-ai, manulife-maude
A37: UW-05 | B37: Souscription | C37: Génératif | D37: H1 | E37: L2 | F37: Haut risque | G37: 4 | H37: 3 | I37: Lecture des rapports médicaux | J37: doc, mrm | K37: er, gr | L37: scor-ai
A38: UW-06 | B38: Souscription | C38: ML prédictif | D38: H1 | E38: L2 | F38: Minimal | G38: 4 | H38: 3 | I38: Inspection à distance par imagerie | J38: cv, geo | K38: lr, er
A39: UW-07 | B39: Souscription | C39: Agentique | D39: H2 | E39: L3 | F39: Minimal | G39: 5 | H39: 3 | I39: Agent de souscription PME de bout en bout | J39: orch, price, doc, ext | K39: gr, er, lr
A40: UW-08 | B40: Souscription | C40: Jumeau | D40: H1 | E40: L2 | F40: Minimal | G40: 4 | H40: 3 | I40: Contrôle des cumuls et de l'exposition en temps réel | J40: geo, sim | K40: cap, lr
A41: UW-09 | B41: Souscription | C41: Génératif | D41: H1 | E41: L2 | F41: Minimal | G41: 4 | H41: 4 | I41: Analyse des clauses et exclusions | J41: doc, kb | K41: lr, risk
A42: UW-10 | B42: Souscription | C42: Agentique | D42: H1 | E42: L3 | F42: Minimal | G42: 4 | H42: 4 | I42: Renouvellements automatisés avec revue par exception | J42: orch, price | K42: er, lr, gr
A43: POL-01 | B43: Contrats | C43: Agentique | D43: H1 | E43: L3 | F43: Minimal | G43: 4 | H43: 4 | I43: Traitement automatisé des avenants et demandes | J43: orch, doc | K43: er, cx
A44: POL-02 | B44: Contrats | C44: Agentique | D44: H1 | E44: L3 | F44: Transparence | G44: 4 | H44: 4 | I44: Agent de service client omnicanal | J44: conv, orch, kb | K44: cx, er | L44: pingan-ai
A45: POL-03 | B45: Contrats | C45: Génératif | D45: H1 | E45: L2 | F45: Minimal | G45: 3 | H45: 5 | I45: Assistant du gestionnaire sur les procédures | J45: kb | K45: er, cx
A46: POL-04 | B46: Contrats | C46: ML prédictif | D46: H1 | E46: L4 | F46: Minimal | G46: 3 | H46: 5 | I46: Classification et routage des flux entrants | J46: doc | K46: er | L46: axa-hub
A47: POL-05 | B47: Contrats | C47: Agentique | D47: H1 | E47: L3 | F47: Minimal | G47: 3 | H47: 4 | I47: Gestion des contrats collectifs et des affiliations | J47: doc, orch | K47: er
A48: POL-06 | B48: Contrats | C48: ML prédictif | D48: H1 | E48: L3 | F48: Minimal | G48: 3 | H48: 4 | I48: Encaissement et recouvrement intelligents | J48: c360 | K48: er, gr
A49: POL-07 | B49: Contrats | C49: Génératif | D49: H1 | E49: L2 | F49: Minimal | G49: 3 | H49: 5 | I49: Analyse des réclamations et de la voix du client | J49: doc, kb | K49: cx, risk
A50: POL-08 | B50: Contrats | C50: Agentique | D50: H1 | E50: L3 | F50: Minimal | G50: 3 | H50: 4 | I50: Recherche des bénéficiaires et contrats non réclamés | J50: c360, orch, doc | K50: risk, cx | L50: generali-fr
A51: PRV-01 | B51: Prévention | C51: Agentique | D51: H1 | E51: L3 | F51: Minimal | G51: 4 | H51: 3 | I51: Alertes de prévention climatique personnalisées | J51: geo, orch, conv | K51: lr, cx
A52: PRV-02 | B52: Prévention | C52: ML prédictif | D52: H1 | E52: L2 | F52: Minimal | G52: 3 | H52: 3 | I52: Coaching de conduite | J52: ext | K52: lr
A53: PRV-03 | B53: Prévention | C53: Génératif | D53: H2 | E53: L2 | F53: Transparence | G53: 4 | H53: 3 | I53: Accompagnement santé et bien-être personnalisé | J53: conv, c360 | K53: lr, cx
A54: PRV-04 | B54: Prévention | C54: ML prédictif | D54: H1 | E54: L2 | F54: Minimal | G54: 3 | H54: 3 | I54: Détection des fuites et sinistres par capteurs | J54: ext | K54: lr
A55: PRV-05 | B55: Prévention | C55: Agentique | D55: H2 | E55: L3 | F55: Minimal | G55: 4 | H55: 3 | I55: Prévention cyber guidée pour les PME | J55: ext, orch | K55: lr, gr
A56: PRV-06 | B56: Prévention | C56: ML prédictif | D56: H2 | E56: L2 | F56: Minimal | G56: 4 | H56: 3 | I56: Prévention de l'absentéisme en contrats collectifs | J56: c360 | K56: lr, risk
A57: CLM-01 | B57: Sinistres | C57: Agentique | D57: H1 | E57: L3 | F57: Transparence | G57: 4 | H57: 4 | I57: Déclaration de sinistre conversationnelle | J57: conv, doc, orch | K57: cx, er | L57: lemonade
A58: CLM-02 | B58: Sinistres | C58: ML prédictif | D58: H1 | E58: L4 | F58: Minimal | G58: 5 | H58: 4 | I58: Triage et orientation des sinistres | J58: orch, doc | K58: lr, er, cx
A59: CLM-03 | B59: Sinistres | C59: ML prédictif | D59: H1 | E59: L3 | F59: Minimal | G59: 4 | H59: 4 | I59: Expertise automobile sur photos | J59: cv | K59: lr, er, cx | L59: aviva-tractable, covea-tractable, pingan-ai
A60: CLM-04 | B60: Sinistres | C60: ML prédictif | D60: H1 | E60: L2 | F60: Minimal | G60: 4 | H60: 3 | I60: Expertise habitation à distance | J60: cv, doc | K60: lr, er, cx
A61: CLM-05 | B61: Sinistres | C61: Agentique | D61: H1 | E61: L4 | F61: Minimal | G61: 5 | H61: 3 | I61: Règlement automatique des sinistres simples | J61: orch, doc | K61: er, cx | L61: allianz-nemo, lemonade, axa-hub, celent-2025
A62: CLM-06 | B62: Sinistres | C62: Agentique | D62: H1 | E62: L3 | F62: Minimal | G62: 5 | H62: 3 | I62: Gestion des pics de sinistres climatiques | J62: orch, geo, doc | K62: cx, er, lr | L62: allianz-nemo
A63: CLM-07 | B63: Sinistres | C63: Génératif | D63: H1 | E63: L2 | F63: Minimal | G63: 4 | H63: 5 | I63: Copilote du gestionnaire sinistres | J63: kb, doc | K63: er, cx | L63: allstate-genai
A64: CLM-08 | B64: Sinistres | C64: Génératif | D64: H1 | E64: L2 | F64: Minimal | G64: 3 | H64: 5 | I64: Rédaction des communications sinistres | J64: kb | K64: cx, er | L64: allstate-genai
A65: CLM-09 | B65: Sinistres | C65: Génératif | D65: H1 | E65: L2 | F65: Minimal | G65: 4 | H65: 4 | I65: Analyse de couverture assistée | J65: doc, kb | K65: lr, er
A66: CLM-10 | B66: Sinistres | C66: ML prédictif | D66: H1 | E66: L2 | F66: Minimal | G66: 4 | H66: 4 | I66: Détection des opportunités de recours | J66: doc, graph | K66: lr
A67: CLM-11 | B67: Sinistres | C67: Génératif | D67: H2 | E67: L2 | F67: Minimal | G67: 5 | H67: 3 | I67: Sinistres corporels et graves : évaluation assistée | J67: doc, kb, mrm | K67: lr, cap
A68: CLM-12 | B68: Sinistres | C68: Optimisation / quantique | D68: H1 | E68: L3 | F68: Minimal | G68: 4 | H68: 4 | I68: Orientation vers les réseaux de réparation | J68: opt, cv | K68: lr, cx
A69: CLM-13 | B69: Sinistres | C69: Agentique | D69: H1 | E69: L4 | F69: Minimal | G69: 4 | H69: 4 | I69: Remboursements santé automatisés | J69: doc, orch | K69: er, cx | L69: pingan-ai, pingan-life, bupa-arabia
A70: CLM-14 | B70: Sinistres | C70: Agentique | D70: H1 | E70: L3 | F70: Minimal | G70: 4 | H70: 3 | I70: Instruction des prestations décès, arrêt et invalidité | J70: doc, orch, kb | K70: er, cx
A71: CLM-15 | B71: Sinistres | C71: Agentique | D71: H1 | E71: L3 | F71: Minimal | G71: 4 | H71: 4 | I71: Revue qualité des sinistres clos | J71: orch, doc, mrm | K71: lr
A72: CLM-16 | B72: Sinistres | C72: Génératif | D72: H2 | E72: L2 | F72: Minimal | G72: 4 | H72: 3 | I72: Sinistres complexes et contentieux : préparation juridique | J72: doc, kb | K72: lr, er
A73: FRD-01 | B73: Fraude | C73: ML prédictif | D73: H1 | E73: L3 | F73: Minimal | G73: 5 | H73: 4 | I73: Score de fraude sinistres en temps réel | J73: graph, doc | K73: lr | L73: allianz-incognito, pingan-ai
A74: FRD-02 | B74: Fraude | C74: ML prédictif | D74: H1 | E74: L2 | F74: Minimal | G74: 5 | H74: 3 | I74: Analyse de réseaux et fraude organisée | J74: graph, c360 | K74: lr
A75: FRD-03 | B75: Fraude | C75: ML prédictif | D75: H1 | E75: L3 | F75: Minimal | G75: 5 | H75: 3 | I75: Détection des preuves générées ou manipulées par IA | J75: cv, doc | K75: lr, risk | L75: aviva-fraud
A76: FRD-04 | B76: Fraude | C76: ML prédictif | D76: H1 | E76: L3 | F76: Minimal | G76: 4 | H76: 3 | I76: Fraude à la souscription et faux intermédiaires | J76: graph, c360 | K76: lr, gr | L76: aviva-fraud
A77: FRD-05 | B77: Fraude | C77: Agentique | D77: H2 | E77: L2 | F77: Minimal | G77: 4 | H77: 3 | I77: Agent d'appui à l'enquête | J77: orch, graph, doc | K77: lr, er
A78: FRD-06 | B78: Fraude | C78: ML prédictif | D78: H1 | E78: L2 | F78: Minimal | G78: 4 | H78: 3 | I78: Fraude et abus des prestataires de santé | J78: graph, doc | K78: lr | L78: tawuniya
A79: RE-01 | B79: Réassurance | C79: Optimisation / quantique | D79: H1 | E79: L2 | F79: Minimal | G79: 5 | H79: 3 | I79: Optimisation du programme de réassurance | J79: opt, sim | K79: cap, lr
A80: RE-02 | B80: Réassurance | C80: Génératif | D80: H1 | E80: L3 | F80: Minimal | G80: 4 | H80: 4 | I80: Structuration des bordereaux et comptes | J80: doc | K80: er, cap
A81: RE-03 | B81: Réassurance | C81: Agentique | D81: H2 | E81: L2 | F81: Minimal | G81: 3 | H81: 3 | I81: Préparation des renouvellements de réassurance | J81: orch, doc, sim | K81: cap, er
A82: RE-04 | B82: Réassurance | C82: Génératif | D82: H1 | E82: L2 | F82: Minimal | G82: 3 | H82: 4 | I82: Contrôle des clauses de traités | J82: doc, kb | K82: risk, cap
A83: RE-05 | B83: Réassurance | C83: Agentique | D83: H1 | E83: L3 | F83: Minimal | G83: 4 | H83: 4 | I83: Recouvrements de réassurance et réconciliation | J83: orch, doc | K83: cap, lr
A84: RE-06 | B84: Réassurance | C84: Jumeau | D84: H2 | E84: L2 | F84: Minimal | G84: 5 | H84: 2 | I84: Modélisation des catastrophes naturelles augmentée | J84: geo, sim | K84: cap, lr
A85: RES-01 | B85: Provisions | C85: ML prédictif | D85: H1 | E85: L2 | F85: Minimal | G85: 5 | H85: 3 | I85: Provisionnement ligne à ligne par machine learning | J85: mrm, doc | K85: cap
A86: RES-02 | B86: Provisions | C86: Agentique | D86: H2 | E86: L3 | F86: Minimal | G86: 5 | H86: 3 | I86: Agent de clôture actuarielle | J86: orch, mrm | K86: cap, er
A87: RES-03 | B87: Provisions | C87: ML prédictif | D87: H1 | E87: L2 | F87: Minimal | G87: 4 | H87: 4 | I87: Détection précoce des dérives de sinistralité | J87: mrm | K87: cap, lr
A88: RES-04 | B88: Provisions | C88: Génératif | D88: H1 | E88: L2 | F88: Minimal | G88: 4 | H88: 4 | I88: Rédaction des rapports actuariels et réglementaires | J88: doc, kb | K88: risk, er | L88: sii-review
A89: RES-05 | B89: Provisions | C89: Agentique | D89: H2 | E89: L3 | F89: Minimal | G89: 4 | H89: 3 | I89: IFRS 17 : analyse des mouvements et réconciliations | J89: orch, doc | K89: cap, er
A90: RES-06 | B90: Provisions | C90: Agentique | D90: H2 | E90: L3 | F90: Minimal | G90: 4 | H90: 3 | I90: Validation indépendante et réplication de modèles | J90: code, mrm, orch | K90: risk
A91: RES-07 | B91: Provisions | C91: Jumeau | D91: H2 | E91: L2 | F91: Minimal | G91: 5 | H91: 2 | I91: Jumeau numérique de la clôture | J91: sim | K91: cap
A92: RES-08 | B92: Provisions | C92: Agentique | D92: H1 | E92: L3 | F92: Minimal | G92: 4 | H92: 4 | I92: Qualité des données actuarielles | J92: orch, mrm | K92: cap, risk
A93: CAP-01 | B93: Capital & ALM | C93: ML prédictif | D93: H1 | E93: L2 | F93: Minimal | G93: 5 | H93: 3 | I93: Fonctions proxy par machine learning pour le capital | J93: sim, mrm | K93: cap
A94: CAP-02 | B94: Capital & ALM | C94: Jumeau | D94: H2 | E94: L2 | F94: Minimal | G94: 5 | H94: 2 | I94: Jumeau numérique du bilan et ORSA continu | J94: sim | K94: cap, risk
A95: CAP-03 | B95: Capital & ALM | C95: ML prédictif | D95: H2 | E95: L2 | F95: Minimal | G95: 4 | H95: 3 | I95: Générateur de scénarios économiques et climatiques | J95: sim | K95: cap, risk
A96: CAP-04 | B96: Capital & ALM | C96: Optimisation / quantique | D96: H2 | E96: L2 | F96: Minimal | G96: 5 | H96: 2 | I96: Optimisation ALM et allocation stratégique d'actifs | J96: opt, sim | K96: cap
A97: CAP-05 | B97: Capital & ALM | C97: Génératif | D97: H1 | E97: L2 | F97: Minimal | G97: 3 | H97: 4 | I97: Recherche d'investissement et analyse ESG | J97: doc, kb | K97: cap, risk
A98: CAP-06 | B98: Capital & ALM | C98: Optimisation / quantique | D98: H3 | E98: L1 | F98: Minimal | G98: 5 | H98: 1 | I98: Calcul quantique du risque | J98: sim | K98: cap | L98: baj-quantum, arxiv-quantum, iag-bluequbit
A99: CAP-07 | B99: Capital & ALM | C99: Optimisation / quantique | D99: H2 | E99: L2 | F99: Minimal | G99: 5 | H99: 3 | I99: Allocation du capital par ligne, produit et segment | J99: opt, sim | K99: cap, gr | L99: allstate-ibm-quantum
A100: CAP-08 | B100: Capital & ALM | C100: ML prédictif | D100: H2 | E100: L2 | F100: Minimal | G100: 4 | H100: 3 | I100: Risque de liquidité et rachats massifs | J100: sim | K100: cap, risk
A101: RSK-01 | B101: Risques | C101: Agentique | D101: H1 | E101: L3 | F101: Minimal | G101: 4 | H101: 4 | I101: Inventaire et classification des systèmes d'IA | J101: mrm, orch | K101: risk | L101: eiopa-opinion, eiopa-genai, evident-2026, cbuae-ai, sdaia-framework
...
